{
  "translations": {
    "de": {
      "If no NUKI ID is available, the NUKI ID can be determined in the NUKI Bridge instance in the developer area under SHOW INFO.": "Sollte keine NUKI ID vorhanden sein, so kann die NUKI ID in der NUKI Bridge Instanz im Entwicklerbereich unter INFO ANZEIGEN ermittelt werden.",
      "Description": "Bezeichnung",
      "Action area": "Aktionsbereich",
      "Update State": "Status aktualisieren",
      "Deactivate Ring to Open": "Ring to Open deaktivieren",
      "Activate Ring to Open": "Ring to Open aktivieren",
      "Deactivate Continuous Mode": "Dauermodus deaktivieren",
      "Activate Continuous Mode": "Dauermodus aktivieren",
      "Actuate Door Buzzer": "Türsummer betätigen",
      "NUKI Opener will be created": "NUKI Opener wird erstellt",
      "NUKI Opener is active": "NUKI Opener ist aktiv",
      "NUKI Opener will be deleted": "NUKI Opener wird gelöscht",
      "NUKI Opener is inactive": "NUKI Opener ist inaktiv",
      "NUKI Opener configuration has an error!": "NUKI Opener Konfiguration hat einen Fehler!",
      "An unknown error has occurred!": "Es ist ein unbekannter Fehler aufgetreten!",
      "Actuate": "Betätigen",
      "Door buzzer": "Türsummer",
      "Mode": "Modus",
      "State": "Status",
      "Battery": "Batterie",
      "Door Mode": "Türmodus",
      "Continuous Mode": "Dauermodus",
      "Unknown": "Unbekannt",
      "Untrained": "Nicht konfiguriert",
      "Ring to Open active": "Ring to Open aktiv",
      "Opening": "Wird geöffnet",
      "Undefined": "Undefiniert"
    }
  }
}
